<?xml version="1.0" encoding="UTF-8"?>
<!DOCTYPE beans PUBLIC "-//SPRING//DTD BEAN//EN"
   "http://www.springframework.org/dtd/spring-beans.dtd">

<beans>

	<bean id="dbexUserService" class="com.gs.dbex.service.impl.DbexUserServiceImpl">
		<property name="dbexUserDao" ref="dbexUserDao"></property>
	</bean>
	
	<bean id="connectionPropertiesService" class="com.gs.dbex.service.impl.ConnectionPropertiesServiceImpl">
		<property name="connectionPropertiesDao" ref="connectionPropertiesDao"></property>
	</bean>
	
</beans>